RTL/IP_Parser/ip_parser_input_fifo.sv
`timescale 1ns / 1ps

module ip_parser_input_fifo # (
    parameter DEPTH = 512,                      // Max num of words
    parameter ADDRW = $clog2(DEPTH)             // Num of bits needed
)(
    input   logic           clk,
    input   logic           rst_n,

    // Write Interface (From the Frame Parser)
    input   logic [63:0]    s_axis_tdata,       // 8 bytes of packet data per clock cycle, starting at byte 0 of the IP header. Big-endian, matching wire order.
    input   logic [7:0]     s_axis_tkeep,       // Valid byte mask. 0xFF on all beats except the last, where it indicates how many trailing bytes are real data.
    input   logic           s_axis_tvalid,      // Data is valid and ready to be consumed.
    output  logic           s_axis_tready,      // Backpressure from the IP parser back upstream. If low, upstream must hold data stable.
    input   logic           s_axis_tlast,       // High on the final beat of the packet.
    input   logic [0:0]     s_axis_tuser,       // FCS error flag propagated from the MAC. If high, the frame had a bad CRC and should be discarded here too.

    // Read Interface (To IP Parser logic)
    output  logic [63:0]    m_axis_tdata,
    output  logic [7:0]     m_axis_tkeep,
    output  logic           m_axis_tvalid,
    input   logic           m_axis_tready,
    output  logic           m_axis_tlast,
    output  logic [0:0]     m_axis_tuser
);

// Internal Signal Packing
localparam DATAW = 64 + 8 + 1 + 1;              // tdata + tkeep + tlast + tuser
logic [DATAW-1:0] write_word;
logic [DATAW-1:0] read_word;

assign write_word = {s_axis_tuser, s_axis_tlast, s_axis_tkeep, s_axis_tdata};   // Bundles into a single 74-bit cable
assign {m_axis_tuser, m_axis_tlast, m_axis_tkeep, m_axis_tdata} = read_word;    // Splits 74-bit into individual wires

// Interface Memory and Pointers
logic [DATAW-1:0] mem [0:DEPTH-1];              // Builds RAM block 74 bits wide and 512 entries deep
logic [ADDRW-1:0] rd_ptr, wr_ptr;               // Addresses to row to write/read to
logic [ADDRW:0] occupancy;

// Handshaking and Backpressure Logic
logic full, empty, push, pop;
logic read_en, valid_r;

assign push = s_axis_tvalid && s_axis_tready;
assign pop  = m_axis_tvalid && m_axis_tready;

assign full  = (occupancy == DEPTH);
assign empty = (occupancy == 0);

// First-Word Fall-Through (Using BRAM)
assign read_en = ~empty && (~valid_r || pop);

// tready goes high if fifo isn't full, or if we are making room by fetching from BRAM this cycle
assign s_axis_tready = ~full || read_en;
assign m_axis_tvalid = valid_r;

always_ff @(posedge clk) begin
    if (push) begin
        mem[wr_ptr] <= write_word;
    end
    if (read_en) begin
        if (push && (wr_ptr == rd_ptr)) begin
            // COLLISION CASE: Writing and reading the same address.
            // Because of Non-Blocking Assignment (<=) rules in simulation, 
            // mem[rd_ptr] is sampled BEFORE the 'push' write actually commits.
            // This forces the simulator to read the OLD data.
            read_word <= mem[rd_ptr];
        end else begin
            // NORMAL CASE: Reading a different address.
            read_word <= mem[rd_ptr];
        end
    end
end

// Synchronous Block (Made from DFFs)
always_ff @(posedge clk or negedge rst_n) begin
    // Reset condition
    if (!rst_n) begin
        rd_ptr      <= 'd0;
        wr_ptr      <= 'd0;
        occupancy   <= 'd0;
        valid_r     <= 1'b0;
    end else begin
        // Output validity tracking
        if (read_en)      valid_r <= 1'b1;
        else if (pop)     valid_r <= 1'b0;

        // Push & BRAM Read simultaneously (Occupancy doesn't change here)
        if (push && read_en) begin
            wr_ptr <= wr_ptr + 1;
            rd_ptr <= rd_ptr + 1;
        end
        // Push only
        else if (push) begin
            wr_ptr      <= wr_ptr + 1;
            occupancy   <= occupancy + 1;
        end
        // BRAM Read only
        else if (read_en) begin
            rd_ptr      <= rd_ptr + 1;
            occupancy   <= occupancy - 1;
        end
    end
end

endmodule

verification/IP_Parser/tb_ip_input_fifo.sv
`timescale 1ns/1ps

//==========================================
// Testbench for IP Parser Input fifo
//==========================================

module tb_ip_parser_input_fifo ();
    // Parameters and Clock/Reset Generation
    parameter DEPTH = 16; // Smaller than RTL for faster simulation
    parameter ADDRW = $clog2(DEPTH);
    localparam DATAW = 64 + 8 + 1 + 1;

    logic clk, rst_n;

    // 100 MHz Clock generation
    initial begin
        clk = 1'b0;
        forever #5 clk = ~clk;
    end

    // DUT Interface Signals
    logic [63:0]    s_axis_tdata;
    logic [7:0]     s_axis_tkeep;
    logic           s_axis_tvalid;
    logic           s_axis_tready;
    logic           s_axis_tlast;
    logic [0:0]     s_axis_tuser;

    logic [63:0]    m_axis_tdata;
    logic [7:0]     m_axis_tkeep;
    logic           m_axis_tvalid;
    logic           m_axis_tready;
    logic           m_axis_tlast;
    logic [0:0]     m_axis_tuser;

    // DUT Instantiation
    ip_parser_input_fifo #(
        .DEPTH(DEPTH),
        .ADDRW(ADDRW)
    ) dut (
        .clk(clk),
        .rst_n(rst_n),
        .s_axis_tdata(s_axis_tdata),
        .s_axis_tkeep(s_axis_tkeep),
        .s_axis_tvalid(s_axis_tvalid),
        .s_axis_tready(s_axis_tready),
        .s_axis_tlast(s_axis_tlast),
        .s_axis_tuser(s_axis_tuser),
        .m_axis_tdata(m_axis_tdata),
        .m_axis_tkeep(m_axis_tkeep),
        .m_axis_tvalid(m_axis_tvalid),
        .m_axis_tready(m_axis_tready),
        .m_axis_tlast(m_axis_tlast),
        .m_axis_tuser(m_axis_tuser)
    );

    // Score and test tracking
    integer errors = 0;
    integer i;
 
    // Used by the random back-and-forth in Test 4 below
    localparam RANDOM_ITEMS = 30;
    integer write_val, read_val;
    logic   write_handshake, read_handshake;


    task reset_env();
        rst_n = 0;
        s_axis_tvalid = 0;
        s_axis_tdata = '0;
        s_axis_tkeep = '0;
        s_axis_tlast = 0;
        s_axis_tuser = 0;
        m_axis_tready = 1;
        repeat(5) @(posedge clk);
        rst_n = 1;
        @(posedge clk);
        $display("[TB] System Reset Complete.");
    endtask

    // Small if/else helper borrowed from tb_ip_parser_header_extraction.sv
    task check(input cond, input string msg);
        if (cond)
            $display("PASS: %0s", msg);
        else begin
            $display("FAIL: %0s", msg);
            errors = errors + 1;
        end
    endtask


    // Main Test Flow
    initial begin
        // Dump a waveform so we can look at this in GTKWave afterward
        $dumpfile("tb_ip_parser_input_fifo.vcd");
        $dumpvars(0, tb_ip_parser_input_fifo);

        // Reset
        reset_env();

        // =============================================
        // Test 1: Write 5 words, read them out in order
        // =============================================
        $display("\n[TB] === Test 1: Basic Read/Write ===");

        s_axis_tvalid   = 1;
        s_axis_tkeep    = 8'hFF;
        m_axis_tready   = 0;

        for (i = 0; i < 5; i = i + 1) begin
            s_axis_tdata = i;
            s_axis_tlast = (i == 4);
            @(posedge clk);
        end
        s_axis_tvalid = 0;
        s_axis_tlast = 0;

        // Let the words sit in the FIFO for a bit
        repeat (3) @(posedge clk);

        m_axis_tready = 1;
        for (i = 0; i < 5; i = i + 1) begin
            while (!m_axis_tvalid)
                @(posedge clk);
            check(m_axis_tdata == i, "Word came back in the right order ?");
            @(posedge clk);
        end
        m_axis_tready = 0;

        repeat (2) @(posedge clk);
        check(m_axis_tvalid == 0, "tvalid drops once the FIFO is empty");

        // Atp, the FIFO should be empty, let's leave tready high and
        // make sure nothing weird comes out while there's nothing to read
        m_axis_tready = 1;
        repeat (5) @(posedge clk);
        check(m_axis_tvalid == 0, "tvalid stays low when reading from an Empty FIFO");
        m_axis_tready = 0;

        // =============================================
        // Test 2: Fill FIFO, meaning tready should drop
        // =============================================
        $display("\n[TB] === Test 2: Fill FIFO until full ===");

        m_axis_tready = 0;      // Don't drain while filling the FIFO
        s_axis_tvalid = 1;
        s_axis_tkeep = 8'hFF;
        i = 0;

        while (s_axis_tready && i <= DEPTH + 1) begin
            s_axis_tdata = i;
            @(posedge clk);
            i = i + 1;
        end

        check(i == DEPTH + 1, "tready dropped after exactly DEPTH words (i.e. when FIFO is full)");

        // FIFO should be full now (s_axis_tready == 0)
        // Let's try to push one more word
        // In theory, it should be rejected and not stored in the FIFO
        s_axis_tdata = 64'hDEAD_BEEF;
        repeat (3) @(posedge clk);
        check(s_axis_tready == 0, "tready stays low while pushing into a full FIFO");
        s_axis_tvalid = 0;

        // Drain it back out and make sure DEADBEEF doesn't show up
        // If it does, the extra word overwrote something :skull:
        m_axis_tready = 1;
        for (i = 0; i < DEPTH + 1; i = i + 1) begin
            while (!m_axis_tvalid)
                @(posedge clk);
            check (m_axis_tdata == i, "drained word matches original data => extra word not stored in FIFO");
            @(posedge clk);
        end
        m_axis_tready = 0;

        // ===============================================
        // Test 3: Reset while transfer is still happening
        // ===============================================
        $display("\n [TB] === Test 3: What happens when reset in middle of a transfer ===");

        s_axis_tvalid = 1;
        s_axis_tkeep  = 8'hFF;
        s_axis_tdata  = 64'hAA;
        @(posedge clk);
        s_axis_tdata  = 64'hBB;
        @(posedge clk);
        s_axis_tvalid = 0;

        rst_n = 0;
        repeat (2) @(posedge clk);
        check(m_axis_tvalid == 0, "tvalid low during reset");

        rst_n = 1;
        @(posedge clk);

        // Let's try to push one new word after reset !
        // If pointers didn't actually reset, we would get something mixed up with old AA/BB data
        s_axis_tvalid = 1;
        s_axis_tdata = 64'hCC;
        @(posedge clk);
        s_axis_tvalid = 0;

        m_axis_tready = 1;
        while (!m_axis_tvalid)
            @(posedge clk);
        check(m_axis_tdata == 64'hCC, "FIFO reset cleanly");
        @(posedge clk);
        m_axis_tready = 0;

        // =============================================
        // Test 4: Random back-and-forth read and writes
        // =============================================
        $display("\n [TB] === Test 4: Random read/writes ===");

        write_val = 0;
        read_val  = 0;
        s_axis_tkeep  = 8'hFF;
        s_axis_tlast  = 0;

        while (read_val < RANDOM_ITEMS) begin
            // Randomly decide whether to offer a push and accept a pop
            s_axis_tvalid = (write_val < RANDOM_ITEMS) && ($random % 2 == 0);
            m_axis_tready = ($random % 2 == 0);
            if (s_axis_tvalid)
                s_axis_tdata = write_val;
 
            write_handshake = s_axis_tvalid && s_axis_tready;
            read_handshake  = m_axis_tvalid && m_axis_tready;
 
            if (read_handshake)
                check(m_axis_tdata == read_val, "random test: words came back in order");
 
            @(posedge clk);
 
            if (write_handshake) write_val = write_val + 1;
            if (read_handshake)  read_val  = read_val + 1;
        end

        s_axis_tvalid = 0;
        m_axis_tready = 0;

        // --- Summary ---
        if (errors == 0)
            $display("\nALL TESTS PASSED");
        else
            $display("\n%0d TEST(S) FAILED", errors);

        $finish;
    end
endmodule

/*
VERILATOR COMMAND TEST
verilator --binary -j 0 --timing --trace --trace-structs -Wall -Wno-fatal RTL/IP_Parser/ip_parser_input_fifo.sv verification/IP_Parser/tb_ip_input_fifo.sv --top-module tb_ip_parser_input_fifo

RUN TEST
./obj_dir/Vtb_ip_parser_input_fifo
*/

verification/IP_Parser/tb_ip_parser_input_fifo.vcd
$version Generated by VerilatedVcd $end
$timescale 1ps $end
 $scope module tb_ip_parser_input_fifo $end
  $var wire 32 v DEPTH [31:0] $end
  $var wire 32 w ADDRW [31:0] $end
  $var wire 32 x DATAW [31:0] $end
  $var wire 1 p clk $end
  $var wire 1 " rst_n $end
  $var wire 64 # s_axis_tdata [63:0] $end
  $var wire 8 % s_axis_tkeep [7:0] $end
  $var wire 1 & s_axis_tvalid $end
  $var wire 1 q s_axis_tready $end
  $var wire 1 ' s_axis_tlast $end
  $var wire 1 ( s_axis_tuser [0:0] $end
  $var wire 64 2 m_axis_tdata [63:0] $end
  $var wire 8 4 m_axis_tkeep [7:0] $end
  $var wire 1 j m_axis_tvalid $end
  $var wire 1 ) m_axis_tready $end
  $var wire 1 5 m_axis_tlast $end
  $var wire 1 6 m_axis_tuser [0:0] $end
  $var wire 32 r errors [31:0] $end
  $var wire 32 * i [31:0] $end
  $var wire 32 y RANDOM_ITEMS [31:0] $end
  $var wire 32 + write_val [31:0] $end
  $var wire 32 , read_val [31:0] $end
  $var wire 1 - write_handshake $end
  $var wire 1 . read_handshake $end
  $scope module dut $end
   $var wire 32 v DEPTH [31:0] $end
   $var wire 32 w ADDRW [31:0] $end
   $var wire 1 p clk $end
   $var wire 1 " rst_n $end
   $var wire 64 # s_axis_tdata [63:0] $end
   $var wire 8 % s_axis_tkeep [7:0] $end
   $var wire 1 & s_axis_tvalid $end
   $var wire 1 q s_axis_tready $end
   $var wire 1 ' s_axis_tlast $end
   $var wire 1 ( s_axis_tuser [0:0] $end
   $var wire 64 2 m_axis_tdata [63:0] $end
   $var wire 8 4 m_axis_tkeep [7:0] $end
   $var wire 1 j m_axis_tvalid $end
   $var wire 1 ) m_axis_tready $end
   $var wire 1 5 m_axis_tlast $end
   $var wire 1 6 m_axis_tuser [0:0] $end
   $var wire 32 x DATAW [31:0] $end
   $var wire 74 / write_word [73:0] $end
   $var wire 74 7 read_word [73:0] $end
   $var wire 74 : mem[0] [73:0] $end
   $var wire 74 = mem[1] [73:0] $end
   $var wire 74 @ mem[2] [73:0] $end
   $var wire 74 C mem[3] [73:0] $end
   $var wire 74 F mem[4] [73:0] $end
   $var wire 74 I mem[5] [73:0] $end
   $var wire 74 L mem[6] [73:0] $end
   $var wire 74 O mem[7] [73:0] $end
   $var wire 74 R mem[8] [73:0] $end
   $var wire 74 U mem[9] [73:0] $end
   $var wire 74 X mem[10] [73:0] $end
   $var wire 74 [ mem[11] [73:0] $end
   $var wire 74 ^ mem[12] [73:0] $end
   $var wire 74 a mem[13] [73:0] $end
   $var wire 74 d mem[14] [73:0] $end
   $var wire 74 g mem[15] [73:0] $end
   $var wire 4 k rd_ptr [3:0] $end
   $var wire 4 l wr_ptr [3:0] $end
   $var wire 5 m occupancy [4:0] $end
   $var wire 1 n full $end
   $var wire 1 o empty $end
   $var wire 1 s push $end
   $var wire 1 t pop $end
   $var wire 1 u read_en $end
   $var wire 1 j valid_r $end
  $upscope $end
 $upscope $end
$enddefinitions $end


#0
0"
b0000000000000000000000000000000000000000000000000000000000000000 #
b00000000 %
0&
0'
0(
1)
b00000000000000000000000000000000 *
b00000000000000000000000000000000 +
b00000000000000000000000000000000 ,
0-
0.
b00000000000000000000000000000000000000000000000000000000000000000000000000 /
b0000000000000000000000000000000000000000000000000000000000000000 2
b00000000 4
05
06
b00000000000000000000000000000000000000000000000000000000000000000000000000 7
b00000000000000000000000000000000000000000000000000000000000000000000000000 :
b00000000000000000000000000000000000000000000000000000000000000000000000000 =
b00000000000000000000000000000000000000000000000000000000000000000000000000 @
b00000000000000000000000000000000000000000000000000000000000000000000000000 C
b00000000000000000000000000000000000000000000000000000000000000000000000000 F
b00000000000000000000000000000000000000000000000000000000000000000000000000 I
b00000000000000000000000000000000000000000000000000000000000000000000000000 L
b00000000000000000000000000000000000000000000000000000000000000000000000000 O
b00000000000000000000000000000000000000000000000000000000000000000000000000 R
b00000000000000000000000000000000000000000000000000000000000000000000000000 U
b00000000000000000000000000000000000000000000000000000000000000000000000000 X
b00000000000000000000000000000000000000000000000000000000000000000000000000 [
b00000000000000000000000000000000000000000000000000000000000000000000000000 ^
b00000000000000000000000000000000000000000000000000000000000000000000000000 a
b00000000000000000000000000000000000000000000000000000000000000000000000000 d
b00000000000000000000000000000000000000000000000000000000000000000000000000 g
0j
b0000 k
b0000 l
b00000 m
0n
1o
0p
1q
b00000000000000000000000000000000 r
0s
0t
0u
b00000000000000000000000000010000 v
b00000000000000000000000000000100 w
b00000000000000000000000001001010 x
b00000000000000000000000000011110 y
#5000
1p
#10000
0p
#15000
1p
#20000
0p
#25000
1p
#30000
0p
#35000
1p
#40000
0p
#45000
1"
1p
#50000
0p
#55000
b11111111 %
1&
0)
b00111111110000000000000000000000000000000000000000000000000000000000000000 /
b00111111110000000000000000000000000000000000000000000000000000000000000000 :
b0001 l
b00001 m
0o
1p
1s
1u
#60000
0p
#65000
b0000000000000000000000000000000000000000000000000000000000000001 #
b00000000000000000000000000000001 *
b00111111110000000000000000000000000000000000000000000000000000000000000001 /
b11111111 4
b00111111110000000000000000000000000000000000000000000000000000000000000000 7
b00111111110000000000000000000000000000000000000000000000000000000000000001 =
1j
b0001 k
b0010 l
1p
0u
#70000
0p
#75000
b0000000000000000000000000000000000000000000000000000000000000010 #
b00000000000000000000000000000010 *
b00111111110000000000000000000000000000000000000000000000000000000000000010 /
b00111111110000000000000000000000000000000000000000000000000000000000000010 @
b0011 l
b00010 m
1p
#80000
0p
#85000
b0000000000000000000000000000000000000000000000000000000000000011 #
b00000000000000000000000000000011 *
b00111111110000000000000000000000000000000000000000000000000000000000000011 /
b00111111110000000000000000000000000000000000000000000000000000000000000011 C
b0100 l
b00011 m
1p
#90000
0p
#95000
b0000000000000000000000000000000000000000000000000000000000000100 #
1'
b00000000000000000000000000000100 *
b01111111110000000000000000000000000000000000000000000000000000000000000100 /
b01111111110000000000000000000000000000000000000000000000000000000000000100 F
b0101 l
b00100 m
1p
#100000
0p
#105000
0&
0'
b00000000000000000000000000000101 *
b00111111110000000000000000000000000000000000000000000000000000000000000100 /
1p
0s
#110000
0p
#115000
1p
#120000
0p
#125000
1p
#130000
0p
#135000
1)
b00000000000000000000000000000000 *
b0000000000000000000000000000000000000000000000000000000000000001 2
b00111111110000000000000000000000000000000000000000000000000000000000000001 7
b0010 k
b00011 m
1p
1t
1u
#140000
0p
#145000
b00000000000000000000000000000001 *
b0000000000000000000000000000000000000000000000000000000000000010 2
b00111111110000000000000000000000000000000000000000000000000000000000000010 7
b0011 k
b00010 m
1p
#150000
0p
#155000
b00000000000000000000000000000010 *
b0000000000000000000000000000000000000000000000000000000000000011 2
b00111111110000000000000000000000000000000000000000000000000000000000000011 7
b0100 k
b00001 m
1p
#160000
0p
#165000
b00000000000000000000000000000011 *
b0000000000000000000000000000000000000000000000000000000000000100 2
15
b01111111110000000000000000000000000000000000000000000000000000000000000100 7
b0101 k
b00000 m
1o
1p
0u
#170000
0p
#175000
b00000000000000000000000000000100 *
0j
1p
0t
#180000
0p
#185000
0)
b00000000000000000000000000000101 *
1p
#190000
0p
#195000
1p
#200000
0p
#205000
1)
1p
#210000
0p
#215000
1p
#220000
0p
#225000
1p
#230000
0p
#235000
1p
#240000
0p
#245000
1p
#250000
0p
#255000
b0000000000000000000000000000000000000000000000000000000000000000 #
1&
0)
b00000000000000000000000000000000 *
b00111111110000000000000000000000000000000000000000000000000000000000000000 /
b00111111110000000000000000000000000000000000000000000000000000000000000000 I
b0110 l
b00001 m
0o
1p
1s
1u
#260000
0p
#265000
b0000000000000000000000000000000000000000000000000000000000000001 #
b00000000000000000000000000000001 *
b00111111110000000000000000000000000000000000000000000000000000000000000001 /
b0000000000000000000000000000000000000000000000000000000000000000 2
05
b00111111110000000000000000000000000000000000000000000000000000000000000000 7
b00111111110000000000000000000000000000000000000000000000000000000000000001 L
1j
b0110 k
b0111 l
1p
0u
#270000
0p
#275000
b0000000000000000000000000000000000000000000000000000000000000010 #
b00000000000000000000000000000010 *
b00111111110000000000000000000000000000000000000000000000000000000000000010 /
b00111111110000000000000000000000000000000000000000000000000000000000000010 O
b1000 l
b00010 m
1p
#280000
0p
#285000
b0000000000000000000000000000000000000000000000000000000000000011 #
b00000000000000000000000000000011 *
b00111111110000000000000000000000000000000000000000000000000000000000000011 /
b00111111110000000000000000000000000000000000000000000000000000000000000011 R
b1001 l
b00011 m
1p
#290000
0p
#295000
b0000000000000000000000000000000000000000000000000000000000000100 #
b00000000000000000000000000000100 *
b00111111110000000000000000000000000000000000000000000000000000000000000100 /
b00111111110000000000000000000000000000000000000000000000000000000000000100 U
b1010 l
b00100 m
1p
#300000
0p
#305000
b0000000000000000000000000000000000000000000000000000000000000101 #
b00000000000000000000000000000101 *
b00111111110000000000000000000000000000000000000000000000000000000000000101 /
b00111111110000000000000000000000000000000000000000000000000000000000000101 X
b1011 l
b00101 m
1p
#310000
0p
#315000
b0000000000000000000000000000000000000000000000000000000000000110 #
b00000000000000000000000000000110 *
b00111111110000000000000000000000000000000000000000000000000000000000000110 /
b00111111110000000000000000000000000000000000000000000000000000000000000110 [
b1100 l
b00110 m
1p
#320000
0p
#325000
b0000000000000000000000000000000000000000000000000000000000000111 #
b00000000000000000000000000000111 *
b00111111110000000000000000000000000000000000000000000000000000000000000111 /
b00111111110000000000000000000000000000000000000000000000000000000000000111 ^
b1101 l
b00111 m
1p
#330000
0p
#335000
b0000000000000000000000000000000000000000000000000000000000001000 #
b00000000000000000000000000001000 *
b00111111110000000000000000000000000000000000000000000000000000000000001000 /
b00111111110000000000000000000000000000000000000000000000000000000000001000 a
b1110 l
b01000 m
1p
#340000
0p
#345000
b0000000000000000000000000000000000000000000000000000000000001001 #
b00000000000000000000000000001001 *
b00111111110000000000000000000000000000000000000000000000000000000000001001 /
b00111111110000000000000000000000000000000000000000000000000000000000001001 d
b1111 l
b01001 m
1p
#350000
0p
#355000
b0000000000000000000000000000000000000000000000000000000000001010 #
b00000000000000000000000000001010 *
b00111111110000000000000000000000000000000000000000000000000000000000001010 /
b00111111110000000000000000000000000000000000000000000000000000000000001010 g
b0000 l
b01010 m
1p
#360000
0p
#365000
b0000000000000000000000000000000000000000000000000000000000001011 #
b00000000000000000000000000001011 *
b00111111110000000000000000000000000000000000000000000000000000000000001011 /
b00111111110000000000000000000000000000000000000000000000000000000000001011 :
b0001 l
b01011 m
1p
#370000
0p
#375000
b0000000000000000000000000000000000000000000000000000000000001100 #
b00000000000000000000000000001100 *
b00111111110000000000000000000000000000000000000000000000000000000000001100 /
b00111111110000000000000000000000000000000000000000000000000000000000001100 =
b0010 l
b01100 m
1p
#380000
0p
#385000
b0000000000000000000000000000000000000000000000000000000000001101 #
b00000000000000000000000000001101 *
b00111111110000000000000000000000000000000000000000000000000000000000001101 /
b00111111110000000000000000000000000000000000000000000000000000000000001101 @
b0011 l
b01101 m
1p
#390000
0p
#395000
b0000000000000000000000000000000000000000000000000000000000001110 #
b00000000000000000000000000001110 *
b00111111110000000000000000000000000000000000000000000000000000000000001110 /
b00111111110000000000000000000000000000000000000000000000000000000000001110 C
b0100 l
b01110 m
1p
#400000
0p
#405000
b0000000000000000000000000000000000000000000000000000000000001111 #
b00000000000000000000000000001111 *
b00111111110000000000000000000000000000000000000000000000000000000000001111 /
b00111111110000000000000000000000000000000000000000000000000000000000001111 F
b0101 l
b01111 m
1p
#410000
0p
#415000
b0000000000000000000000000000000000000000000000000000000000010000 #
b00000000000000000000000000010000 *
b00111111110000000000000000000000000000000000000000000000000000000000010000 /
b00111111110000000000000000000000000000000000000000000000000000000000010000 I
b0110 l
b10000 m
1n
1p
0q
0s
#420000
0p
#425000
b0000000000000000000000000000000011011110101011011011111011101111 #
b00000000000000000000000000010001 *
b00111111110000000000000000000000000000000011011110101011011011111011101111 /
1p
#430000
0p
#435000
1p
#440000
0p
#445000
1p
#450000
0p
#455000
0&
1)
b00000000000000000000000000000000 *
b0000000000000000000000000000000000000000000000000000000000000001 2
b00111111110000000000000000000000000000000000000000000000000000000000000001 7
b0111 k
b01111 m
0n
1p
1q
1t
1u
#460000
0p
#465000
b00000000000000000000000000000001 *
b0000000000000000000000000000000000000000000000000000000000000010 2
b00111111110000000000000000000000000000000000000000000000000000000000000010 7
b1000 k
b01110 m
1p
#470000
0p
#475000
b00000000000000000000000000000010 *
b0000000000000000000000000000000000000000000000000000000000000011 2
b00111111110000000000000000000000000000000000000000000000000000000000000011 7
b1001 k
b01101 m
1p
#480000
0p
#485000
b00000000000000000000000000000011 *
b0000000000000000000000000000000000000000000000000000000000000100 2
b00111111110000000000000000000000000000000000000000000000000000000000000100 7
b1010 k
b01100 m
1p
#490000
0p
#495000
b00000000000000000000000000000100 *
b0000000000000000000000000000000000000000000000000000000000000101 2
b00111111110000000000000000000000000000000000000000000000000000000000000101 7
b1011 k
b01011 m
1p
#500000
0p
#505000
b00000000000000000000000000000101 *
b0000000000000000000000000000000000000000000000000000000000000110 2
b00111111110000000000000000000000000000000000000000000000000000000000000110 7
b1100 k
b01010 m
1p
#510000
0p
#515000
b00000000000000000000000000000110 *
b0000000000000000000000000000000000000000000000000000000000000111 2
b00111111110000000000000000000000000000000000000000000000000000000000000111 7
b1101 k
b01001 m
1p
#520000
0p
#525000
b00000000000000000000000000000111 *
b0000000000000000000000000000000000000000000000000000000000001000 2
b00111111110000000000000000000000000000000000000000000000000000000000001000 7
b1110 k
b01000 m
1p
#530000
0p
#535000
b00000000000000000000000000001000 *
b0000000000000000000000000000000000000000000000000000000000001001 2
b00111111110000000000000000000000000000000000000000000000000000000000001001 7
b1111 k
b00111 m
1p
#540000
0p
#545000
b00000000000000000000000000001001 *
b0000000000000000000000000000000000000000000000000000000000001010 2
b00111111110000000000000000000000000000000000000000000000000000000000001010 7
b0000 k
b00110 m
1p
#550000
0p
#555000
b00000000000000000000000000001010 *
b0000000000000000000000000000000000000000000000000000000000001011 2
b00111111110000000000000000000000000000000000000000000000000000000000001011 7
b0001 k
b00101 m
1p
#560000
0p
#565000
b00000000000000000000000000001011 *
b0000000000000000000000000000000000000000000000000000000000001100 2
b00111111110000000000000000000000000000000000000000000000000000000000001100 7
b0010 k
b00100 m
1p
#570000
0p
#575000
b00000000000000000000000000001100 *
b0000000000000000000000000000000000000000000000000000000000001101 2
b00111111110000000000000000000000000000000000000000000000000000000000001101 7
b0011 k
b00011 m
1p
#580000
0p
#585000
b00000000000000000000000000001101 *
b0000000000000000000000000000000000000000000000000000000000001110 2
b00111111110000000000000000000000000000000000000000000000000000000000001110 7
b0100 k
b00010 m
1p
#590000
0p
#595000
b00000000000000000000000000001110 *
b0000000000000000000000000000000000000000000000000000000000001111 2
b00111111110000000000000000000000000000000000000000000000000000000000001111 7
b0101 k
b00001 m
1p
#600000
0p
#605000
b00000000000000000000000000001111 *
b0000000000000000000000000000000000000000000000000000000000010000 2
b00111111110000000000000000000000000000000000000000000000000000000000010000 7
b0110 k
b00000 m
1o
1p
0u
#610000
0p
#615000
b00000000000000000000000000010000 *
0j
1p
0t
#620000
0p
#625000
b0000000000000000000000000000000000000000000000000000000010101010 #
1&
0)
b00000000000000000000000000010001 *
b00111111110000000000000000000000000000000000000000000000000000000010101010 /
b00111111110000000000000000000000000000000000000000000000000000000010101010 L
b0111 l
b00001 m
0o
1p
1s
1u
#630000
0p
#635000
b0000000000000000000000000000000000000000000000000000000010111011 #
b00111111110000000000000000000000000000000000000000000000000000000010111011 /
b0000000000000000000000000000000000000000000000000000000010101010 2
b00111111110000000000000000000000000000000000000000000000000000000010101010 7
b00111111110000000000000000000000000000000000000000000000000000000010111011 O
1j
b0111 k
b1000 l
1p
0u
#640000
0p
#645000
0"
0&
0j
b0000 k
b0000 l
b00000 m
1o
1p
0s
#650000
0p
#655000
1p
#660000
0p
#665000
1"
1p
#670000
0p
#675000
b0000000000000000000000000000000000000000000000000000000011001100 #
1&
b00111111110000000000000000000000000000000000000000000000000000000011001100 /
b00111111110000000000000000000000000000000000000000000000000000000011001100 :
b0001 l
b00001 m
0o
1p
1s
1u
#680000
0p
#685000
0&
1)
b0000000000000000000000000000000000000000000000000000000011001100 2
b00111111110000000000000000000000000000000000000000000000000000000011001100 7
1j
b0001 k
b00000 m
1o
1p
0s
1t
0u
#690000
0p
#695000
0j
1p
0t
#700000
0p
#705000
b0000000000000000000000000000000000000000000000000000000000000000 #
1&
0)
1-
b00111111110000000000000000000000000000000000000000000000000000000000000000 /
b00111111110000000000000000000000000000000000000000000000000000000000000000 =
b0010 l
b00001 m
0o
1p
1s
1u
#710000
0p
#715000
0&
b00000000000000000000000000000001 +
0-
b0000000000000000000000000000000000000000000000000000000000000000 2
b00111111110000000000000000000000000000000000000000000000000000000000000000 7
1j
b0010 k
b00000 m
1o
1p
0s
0u
#720000
0p
#725000
1)
1.
0j
1p
#730000
0p
#735000
b0000000000000000000000000000000000000000000000000000000000000001 #
1&
b00000000000000000000000000000001 ,
1-
0.
b00111111110000000000000000000000000000000000000000000000000000000000000001 /
b00111111110000000000000000000000000000000000000000000000000000000000000001 @
b0011 l
b00001 m
0o
1p
1s
1u
#740000
0p
#745000
0&
0)
b00000000000000000000000000000010 +
0-
b0000000000000000000000000000000000000000000000000000000000000001 2
b00111111110000000000000000000000000000000000000000000000000000000000000001 7
1j
b0011 k
b00000 m
1o
1p
0s
0u
#750000
0p
#755000
1p
#760000
0p
#765000
1)
1.
0j
1p
#770000
0p
#775000
b00000000000000000000000000000010 ,
0.
1p
#780000
0p
#785000
b0000000000000000000000000000000000000000000000000000000000000010 #
1&
0)
1-
b00111111110000000000000000000000000000000000000000000000000000000000000010 /
b00111111110000000000000000000000000000000000000000000000000000000000000010 C
b0100 l
b00001 m
0o
1p
1s
1u
#790000
0p
#795000
0&
1)
b00000000000000000000000000000011 +
0-
b0000000000000000000000000000000000000000000000000000000000000010 2
b00111111110000000000000000000000000000000000000000000000000000000000000010 7
1j
b0100 k
b00000 m
1o
1p
0s
1t
0u
#800000
0p
#805000
b0000000000000000000000000000000000000000000000000000000000000011 #
1&
1-
1.
b00111111110000000000000000000000000000000000000000000000000000000000000011 /
b00111111110000000000000000000000000000000000000000000000000000000000000011 F
0j
b0101 l
b00001 m
0o
1p
1s
0t
1u
#810000
0p
#815000
0&
b00000000000000000000000000000100 +
b00000000000000000000000000000011 ,
0-
0.
b0000000000000000000000000000000000000000000000000000000000000011 2
b00111111110000000000000000000000000000000000000000000000000000000000000011 7
1j
b0101 k
b00000 m
1o
1p
0s
1t
0u
#820000
0p
#825000
0)
1p
0t
#830000
0p
#835000
b0000000000000000000000000000000000000000000000000000000000000100 #
1&
1)
1-
1.
b00111111110000000000000000000000000000000000000000000000000000000000000100 /
b00111111110000000000000000000000000000000000000000000000000000000000000100 I
0j
b0110 l
b00001 m
0o
1p
1s
1u
#840000
0p
#845000
b0000000000000000000000000000000000000000000000000000000000000101 #
0)
b00000000000000000000000000000101 +
b00000000000000000000000000000100 ,
0.
b00111111110000000000000000000000000000000000000000000000000000000000000101 /
b0000000000000000000000000000000000000000000000000000000000000100 2
b00111111110000000000000000000000000000000000000000000000000000000000000100 7
b00111111110000000000000000000000000000000000000000000000000000000000000101 L
1j
b0110 k
b0111 l
1p
0u
