RTL/MAC/crc_core.sv
`default_nettype none

module CRC_core(
    input wire i_clk,
    input wire i_rstn,
    input wire [63:0] i_8xframe,
    input wire i_valid,
    input wire i_last, 
    input wire i_corrupt,
    output reg [31:0] o_crc
);

    localparam [31:0] init = 32'hFFFF_FFFF;
    localparam [31:0] poly_rev = 32'hEDB8_8320;

    function [31:0] crc_byte;
        input [31:0] c;
        input [7:0] b;
        integer i;
        begin 
            crc_byte = c^{24'h0, b};
            for (i=0; i<8; i=i+1)
                crc_byte = (crc_byte>>1)^(crc_byte[0] ? poly_rev : 32'h0);
        end
    endfunction 

    function [31:0] D;
        input [63:0] x;
        integer k;
        reg [31:0] c;
        begin
            c = 32'h0;
            for (k=0; k<8; k=k+1)
                c = crc_byte(c, x[8*k +: 8]);
                D = c;
        end
    endfunction

    function [31:0] A;
        input [31:0] s;
        integer k;
        reg [31:0] c;
        begin
            c = s;
            for (k=0; k<8; k=k+1)
                c = crc_byte(c, 8'h00);
            A = c;
        end
    endfunction

    reg [31:0] d_pipe;
    reg v_pipe, last_pipe;

    reg [31:0] state;
    reg corrupt_seen;
    wire [31:0] state_next = A(state)^d_pipe;

    always @(posedge i_clk) begin
        if (!i_rstn) begin
            d_pipe <= 32'h0;
            v_pipe <= 1'b0;
            last_pipe <= 1'b0;
            state <= init;
            corrupt_seen <= 1'b0;
            o_crc <= 32'h0;
        end else begin
            d_pipe <= D(i_8xframe);
            v_pipe <= i_valid;
            last_pipe <= i_valid & i_last;

            if (i_corrupt)
                corrupt_seen <= 1'b1;

            if (v_pipe) begin
                if (last_pipe) begin
                    o_crc <= ~state_next ^ (corrupt_seen ? 32'h0000_0001 : 32'h0);
                    state <= init;
                    corrupt_seen <= i_corrupt;
                end else begin
                    state <= state_next;
                end
            end
        end
    end

endmodule

`default_nettype wire

verification/MAC/tb.v
`default_nettype none
`timescale 1ns / 1ps

/* This testbench just instantiates the module and makes some convenient wires
   that can be driven / tested by the cocotb test.py.
*/
module tb ();

  // Dump the signals to a VCD file. You can view it with gtkwave or surfer.
  initial begin
    $dumpfile("tb.vcd");
    $dumpvars(0, tb);
    #1;
  end

  // Wire up the inputs and outputs:
  reg clk;
  reg rstn;
  reg [63:0] i_8xframe;
  reg i_valid;
  reg i_last;
  reg i_corrupt;
  wire [31:0] o_crc;

  // Instantiate control_MAC_learning:
  CRC_core dut (
      .i_clk    (clk),       
      .i_rstn   (rstn),      
      .i_8xframe  (i_8xframe),     
      .i_valid (i_valid),     
      .i_last    (i_last),  
      .i_corrupt (i_corrupt),      
      .o_crc(o_crc)  
  );

endmodule

verification/MAC/tb.vcd
$date
	Thu Jul  9 00:22:19 2026
$end
$version
	Icarus Verilog
$end
$timescale
	1ps
$end
$scope module tb $end
$var wire 32 ! o_crc [31:0] $end
$var reg 1 " clk $end
$var reg 64 # i_8xframe [63:0] $end
$var reg 1 $ i_corrupt $end
$var reg 1 % i_last $end
$var reg 1 & i_valid $end
$var reg 1 ' rstn $end
$scope module dut $end
$var wire 64 ( i_8xframe [63:0] $end
$var wire 1 " i_clk $end
$var wire 1 $ i_corrupt $end
$var wire 1 % i_last $end
$var wire 1 ' i_rstn $end
$var wire 1 & i_valid $end
$var wire 32 ) state_next [31:0] $end
$var parameter 32 * init $end
$var parameter 32 + poly_rev $end
$var reg 1 , corrupt_seen $end
$var reg 32 - d_pipe [31:0] $end
$var reg 1 . last_pipe $end
$var reg 32 / o_crc [31:0] $end
$var reg 32 0 state [31:0] $end
$var reg 1 1 v_pipe $end
$scope function A $end
$var reg 32 2 c [31:0] $end
$var reg 32 3 s [31:0] $end
$var integer 32 4 k [31:0] $end
$upscope $end
$scope function D $end
$var reg 32 5 c [31:0] $end
$var reg 64 6 x [63:0] $end
$var integer 32 7 k [31:0] $end
$upscope $end
$scope function crc_byte $end
$var reg 8 8 b [7:0] $end
$var reg 32 9 c [31:0] $end
$var integer 32 : i [31:0] $end
$upscope $end
$upscope $end
$upscope $end
$enddefinitions $end
$comment Show the parameter values. $end
$dumpall
b11101101101110001000001100100000 +
b11111111111111111111111111111111 *
$end
#0
$dumpvars
b1000 :
b1100010100100110010000010000001 9
b0 8
bx 7
bx 6
bx 5
b1000 4
b11111111111111111111111111111111 3
b10011010110111010010000010010110 2
01
b11111111111111111111111111111111 0
b0 /
0.
b0 -
0,
b10011010110111010010000010010110 )
b0 (
0'
0&
0%
0$
b0 #
1"
b0 !
$end
#4000
0"
#8000
1"
#12000
0"
#16000
1"
#20000
0"
#24000
1'
1"
#28000
0"
#32000
1%
1&
b100000000111000001100000010100000100000000110000001000000001 #
b100000000111000001100000010100000100000000110000001000000001 (
b1000 :
b0 9
b1000 7
b0 5
b0 6
1"
#36000
0"
#40000
0%
0&
b11000000001101010111011100111010 )
1.
11
b1011010111010000101011110101100 -
b11101101100010001011011111110110 9
b1011010111010000101011110101100 5
b1000 :
b1000 8
b1000 7
b100000000111000001100000010100000100000000110000001000000001 6
1"
#44000
0"
#48000
b111111110010101000100011000101 !
b111111110010101000100011000101 /
0.
01
b1000 :
b11101101100010001011011111110110 9
b1000 8
b1000 7
b1011010111010000101011110101100 5
1"
#52000
0"
#56000
1&
b100100001000111010001100100010101000100010000110100001001000001 #
b100100001000111010001100100010101000100010000110100001001000001 (
b1000 :
b11101101100010001011011111110110 9
b1000 8
b1000 7
b1011010111010000101011110101100 5
1"
#60000
0"
#64000
1%
b101000001001111010011100100110101001100010010110100101001001001 #
b101000001001111010011100100110101001100010010110100101001001001 (
b10010111001000110100100111100011 )
11
b1101111111100110100101110101 -
b1000 :
b10010011000000110100101111000010 9
b1001000 8
b1000 7
b1101111111100110100101110101 5
b100100001000111010001100100010101000100010000110100001001000001 6
1"
#68000
0"
#72000
0%
0&
b1000 4
b111110110100101001111010110000 2
b10010111001000110100100111100011 3
b11111000101110000000010110010 )
b10010111001000110100100111100011 0
1.
b100001110001011001111000000010 -
b1000 :
b10111100111010010110101111100111 9
b0 8
b1000 7
b100001110001011001111000000010 5
b101000001001111010011100100110101001100010010110100101001001001 6
1"
#76000
0"
#80000
b10111011000110001011111010010100 )
b1000 4
b10011010110111010010000010010110 2
b11111111111111111111111111111111 3
b11111111111111111111111111111111 0
b11100000111010001111111101001101 !
b11100000111010001111111101001101 /
0.
01
b1000 :
b1100010100100110010000010000001 9
b0 8
b1000 7
b100001110001011001111000000010 5
1"
#84000
0"
#88000
b1000 :
b1110001011010101011011101100100 9
b1010000 8
b1000 7
b100001110001011001111000000010 5
1"
#88001
0'
b0 #
b0 (
#92001
0"
#96001
b10011010110111010010000010010110 )
b0 !
b0 /
b0 -
1"
#100001
0"
#104001
1"
#108001
0"
#112001
1"
#116001
0"
#120001
1'
1"
#124001
0"
#128001
1&
b101011100100000001011000110111101101100011011000110010101001000 #
b101011100100000001011000110111101101100011011000110010101001000 (
b1000 :
b0 9
b0 8
b1000 7
b0 5
b0 6
1"
#132001
0"
#136001
1%
b10011001011011100001101100011001100100011011000111001001101111 #
b10011001011011100001101100011001100100011011000111001001101111 (
b10101000010001100111011111000101 )
11
b110010100110110101011101010011 -
b1000011001110111011000001111011 9
b110010100110110101011101010011 5
b1000 :
b1010111 8
b1000 7
b101011100100000001011000110111101101100011011000110010101001000 6
1"
#140001
0"
#144001
0%
0&
b1000 4
b10000010110111111001101011010000 2
b10101000010001100111011111000101 3
b11011110101110110010000011100011 )
b10101000010001100111011111000101 0
1.
b1011100011001001011101000110011 -
b1000 :
b11010111011011100001000101010110 9
b0 8
b1000 7
b1011100011001001011101000110011 5
b10011001011011100001101100011001100100011011000111001001101111 6
1"
#148001
0"
#152001
b11000110101110011001101010100101 )
b1000 4
b10011010110111010010000010010110 2
b11111111111111111111111111111111 3
b11111111111111111111111111111111 0
b100001010001001101111100011100 !
b100001010001001101111100011100 /
0.
01
b1000 :
b1100010100100110010000010000001 9
b0 8
b1000 7
b1011100011001001011101000110011 5
1"
#156001
0"
#160001
b1000 :
b11010111110100000011011110011101 9
b100110 8
b1000 7
b1011100011001001011101000110011 5
1"
#160002
0'
b0 #
b0 (
#164002
0"
#168002
b10011010110111010010000010010110 )
b0 !
b0 /
b0 -
1"
#172002
0"
#176002
1"
#180002
0"
#184002
1"
#188002
0"
#192002
1'
1"
#196002
0"
#200002
1%
1&
b100000000111000001100000010100000100000000110000001000000001 #
b100000000111000001100000010100000100000000110000001000000001 (
b1000 :
b0 9
b0 8
b1000 7
b0 5
b0 6
1"
#204002
0"
#208002
0%
b100100001000111010001100100010101000100010000110100001001000001 #
b100100001000111010001100100010101000100010000110100001001000001 (
b11000000001101010111011100111010 )
1.
11
b1011010111010000101011110101100 -
b11101101100010001011011111110110 9
b1011010111010000101011110101100 5
b1000 :
b1000 8
b1000 7
b100000000111000001100000010100000100000000110000001000000001 6
1"
#212002
0"
#216002
1%
b101000001001111010011100100110101001100010010110100101001001001 #
b101000001001111010011100100110101001100010010110100101001001001 (
b10010111001000110100100111100011 )
b111111110010101000100011000101 !
b111111110010101000100011000101 /
0.
b1101111111100110100101110101 -
b1000 :
b10010011000000110100101111000010 9
b1001000 8
b1000 7
b1101111111100110100101110101 5
b100100001000111010001100100010101000100010000110100001001000001 6
1"
#220002
0"
#224002
0%
0&
b1000 4
b111110110100101001111010110000 2
b10010111001000110100100111100011 3
b11111000101110000000010110010 )
b10010111001000110100100111100011 0
1.
b100001110001011001111000000010 -
b1000 :
b10111100111010010110101111100111 9
b0 8
b1000 7
b100001110001011001111000000010 5
b101000001001111010011100100110101001100010010110100101001001001 6
1"
#228002
0"
#232002
b10111011000110001011111010010100 )
b1000 4
b10011010110111010010000010010110 2
b11111111111111111111111111111111 3
b11111111111111111111111111111111 0
b11100000111010001111111101001101 !
b11100000111010001111111101001101 /
0.
01
b1000 :
b1100010100100110010000010000001 9
b0 8
b1000 7
b100001110001011001111000000010 5
1"
#236002
0"
#240002
b1000 :
b1110001011010101011011101100100 9
b1010000 8
b1000 7
b100001110001011001111000000010 5
1"
#240003
0'
b0 #
b0 (
#244003
0"
#248003
b10011010110111010010000010010110 )
b0 !
b0 /
b0 -
1"
#252003
0"
#256003
1"
#260003
0"
#264003
1"
#268003
0"
#272003
1'
1"
#276003
0"
#280003
1$
1&
b100100001000111010001100100010101000100010000110100001001000001 #
b100100001000111010001100100010101000100010000110100001001000001 (
b1000 :
b0 9
b0 8
b1000 7
b0 5
b0 6
1"
#284003
0"
#288003
0$
1%
b101000001001111010011100100110101001100010010110100101001001001 #
b101000001001111010011100100110101001100010010110100101001001001 (
b10010111001000110100100111100011 )
1,
11
b1101111111100110100101110101 -
b10010011000000110100101111000010 9
b1101111111100110100101110101 5
b1000 :
b1001000 8
b1000 7
b100100001000111010001100100010101000100010000110100001001000001 6
1"
#292003
0"
#296003
0%
0&
b1000 4
b111110110100101001111010110000 2
b10010111001000110100100111100011 3
b11111000101110000000010110010 )
b10010111001000110100100111100011 0
1.
b100001110001011001111000000010 -
b1000 :
b10111100111010010110101111100111 9
b0 8
b1000 7
b100001110001011001111000000010 5
b101000001001111010011100100110101001100010010110100101001001001 6
1"
#300003
0"
#304003
b10111011000110001011111010010100 )
b1000 4
b10011010110111010010000010010110 2
b11111111111111111111111111111111 3
0,
b11111111111111111111111111111111 0
b11100000111010001111111101001100 !
b11100000111010001111111101001100 /
0.
01
b1000 :
b1100010100100110010000010000001 9
b0 8
b1000 7
b100001110001011001111000000010 5
1"
#308003
0"
#312003
1&
b100100001000111010001100100010101000100010000110100001001000001 #
b100100001000111010001100100010101000100010000110100001001000001 (
b1000 :
b1110001011010101011011101100100 9
b1010000 8
b1000 7
b100001110001011001111000000010 5
1"
#316003
0"
#320003
1%
b101000001001111010011100100110101001100010010110100101001001001 #
b101000001001111010011100100110101001100010010110100101001001001 (
b10010111001000110100100111100011 )
11
b1101111111100110100101110101 -
b1000 :
b10010011000000110100101111000010 9
b1001000 8
b1000 7
b1101111111100110100101110101 5
b100100001000111010001100100010101000100010000110100001001000001 6
1"
#324003
0"
#328003
0%
0&
b1000 4
b111110110100101001111010110000 2
b10010111001000110100100111100011 3
b11111000101110000000010110010 )
b10010111001000110100100111100011 0
1.
b100001110001011001111000000010 -
b1000 :
b10111100111010010110101111100111 9
b0 8
b1000 7
b100001110001011001111000000010 5
b101000001001111010011100100110101001100010010110100101001001001 6
1"
#332003
0"
#336003
b10111011000110001011111010010100 )
b1000 4
b10011010110111010010000010010110 2
b11111111111111111111111111111111 3
b11111111111111111111111111111111 0
b11100000111010001111111101001101 !
b11100000111010001111111101001101 /
0.
01
b1000 :
b1100010100100110010000010000001 9
b0 8
b1000 7
b100001110001011001111000000010 5
1"
#340003
0"
#344003
b1000 :
b1110001011010101011011101100100 9
b1010000 8
b1000 7
b100001110001011001111000000010 5
1"
#344004
0'
b0 #
b0 (
#348004
0"
#352004
b10011010110111010010000010010110 )
b0 !
b0 /
b0 -
1"
#356004
0"
#360004
1"
#364004
0"
#368004
1"
#372004
0"
#376004
1'
1"
#380004
0"
#384004
1&
b1101111010101101101111101110111111011110101011011011111011101111 #
b1101111010101101101111101110111111011110101011011011111011101111 (
b1000 :
b0 9
b0 8
b1000 7
b0 5
b0 6
1"
#388004
0"
#392004
0'
0&
b11000001111100101111110101101 )
11
b10000010111000110111111100111011 -
b11101011100010111111101010001000 9
b10000010111000110111111100111011 5
b1000 :
b11011110 8
b1000 7
b1101111010101101101111101110111111011110101011011011111011101111 6
1"
#396004
0"
#400004
b10011010110111010010000010010110 )
01
b0 -
1"
#404004
0"
#408004
1'
1"
#412004
0"
#416004
1%
1&
b100000000111000001100000010100000100000000110000001000000001 #
b100000000111000001100000010100000100000000110000001000000001 (
b11000001111100101111110101101 )
b10000010111000110111111100111011 -
b1000 :
b11101011100010111111101010001000 9
b11011110 8
b1000 7
b10000010111000110111111100111011 5
1"
#420004
0"
#424004
0%
0&
b11000000001101010111011100111010 )
1.
11
b1011010111010000101011110101100 -
b1000 :
b11101101100010001011011111110110 9
b1000 8
b1000 7
b1011010111010000101011110101100 5
b100000000111000001100000010100000100000000110000001000000001 6
1"
#428004
0"
#432004
b111111110010101000100011000101 !
b111111110010101000100011000101 /
0.
01
b1000 :
b11101101100010001011011111110110 9
b1000 8
b1000 7
b1011010111010000101011110101100 5
1"
#436004
0"
#440004
b1000 :
b11101101100010001011011111110110 9
b1000 8
b1000 7
b1011010111010000101011110101100 5
1"
#440005
0'
b0 #
b0 (
#444005
0"
#448005
b10011010110111010010000010010110 )
b0 !
b0 /
b0 -
1"
#452005
0"
#456005
1"
#460005
0"
#464005
1"
#468005
0"
#472005
1'
1"
#476005
0"
#480005
1&
b111101010111101100001010000011101111010011110101001100110 #
b111101010111101100001010000011101111010011110101001100110 (
b1000 :
b0 9
b0 8
b1000 7
b0 5
b0 6
1"
#484005
0"
#488005
b1110100100110101101110000111000000010111001101000110101101000101 #
b1110100100110101101110000111000000010111001101000110101101000101 (
b111111000101101000110111010000 )
11
b10100101110010111010110101000110 -
b11000001000110000010110100100110 9
b10100101110010111010110101000110 5
b1000 :
b1 8
b1000 7
b111101010111101100001010000011101111010011110101001100110 6
1"
#492005
0"
#496005
b1111000001110011111011101101000111110001010010011111010101000010 #
b1111000001110011111011101101000111110001010010011111010101000010 (
b1000 4
b11001001000100011001111111111 2
b111111000101101000110111010000 3
b1100111010100000111111000011110 )
b111111000101101000110111010000 0
b1111110011100100100110111100001 -
b1000 :
b1001110000001011000111010010110 9
b0 8
b1000 7
b1111110011100100100110111100001 5
b1110100100110101101110000111000000010111001101000110101101000101 6
1"
#500005
0"
#504005
b1001010100001100110111011101100111001110100101111011010110111101 #
b1001010100001100110111011101100111001110100101111011010110111101 (
b1000 4
b11110010111110100010101111000101 2
b1100111010100000111111000011110 3
b1110110001111000010001000011101 )
b1100111010100000111111000011110 0
b10000100110001100000100111011000 -
b1000 :
b10011000001010111000101101010011 9
b0 8
b1000 7
b10000100110001100000100111011000 5
b1111000001110011111011101101000111110001010010011111010101000010 6
1"
#508005
0"
#512005
b1010101111101011100101011001001000001000111100001110101111010100 #
b1010101111101011100101011001001000001000111100001110101111010100 (
b1000 4
b10111010101101101101111011110110 2
b1110110001111000010001000011101 3
b100001100100110111010101110001 )
b1110110001111000010001000011101 0
b10011011001001011010101110000111 -
b1000 :
b1100110111010001111001111110100 9
b0 8
b1000 7
b10011011001001011010101110000111 5
b1001010100001100110111011101100111001110100101111011010110111101 6
1"
#516005
0"
#520005
b1010101111100111110011100011010110001011011100010110101011100 #
b1010101111100111110011100011010110001011011100010110101011100 (
b1000 4
b10111001111110010000110011011011 2
b100001100100110111010101110001 3
b1111111101001101011101111011 )
b100001100100110111010101110001 0
b10110110000011011101101110100000 -
b1000 :
b10011111110110001101001001110110 9
b0 8
b1000 7
b10110110000011011101101110100000 5
b1010101111101011100101011001001000001000111100001110101111010100 6
1"
#524005
0"
#528005
b1100010000111000000110000011011000011001001100100010111111101101 #
b1100010000111000000110000011011000011001001100100010111111101101 (
b1000 4
b10010011000011010111110011010011 2
b1111111101001101011101111011 3
b100111110100111010011000011100 )
b1111111101001101011101111011 0
b10110100110111101101101011001111 -
b1000 :
b100100000110100111010001101 9
b0 8
b1000 7
b10110100110111101101101011001111 5
b1010101111100111110011100011010110001011011100010110101011100 6
1"
#532005
0"
#536005
b11110010011111100100001100100101011010110010010110011000101000 #
b11110010011111100100001100100101011010110010010110011000101000 (
b1000 4
b11101000001001000101111110100101 2
b100111110100111010011000011100 3
b10100001101001011001101011010010 )
b100111110100111010011000011100 0
b1001001100000011100010101110111 -
b1000 :
b10011100100010111001011001000111 9
b0 8
b1000 7
b1001001100000011100010101110111 5
b1100010000111000000110000011011000011001001100100010111111101101 6
1"
#540005
0"
#544005
b11111100011011011010110000000000100011101100010101000100010 #
b11111100011011011010110000000000100011101100010101000100010 (
b1000 4
b1011000101100110111001101000 2
b10100001101001011001101011010010 3
b10100010010001110000010101101100 )
b10100001101001011001101011010010 0
b10101001010100010110101100000100 -
b1000 :
b11001101101100010100100111001111 9
b0 8
b1000 7
b10101001010100010110101100000100 5
b11110010011111100100001100100101011010110010010110011000101000 6
1"
#548005
0"
#552005
b1100100111101101000000100100100011111100100101111001100110100111 #
b1100100111101101000000100100100011111100100101111001100110100111 (
b1000 4
b11001101110001100110110001110001 2
b10100010010001110000010101101100 3
b10100101101111011011110101101000 )
b10100010010001110000010101101100 0
b1101000011110111101000100011001 -
b1000 :
b10001011010101110001011110101 9
b0 8
b1000 7
b1101000011110111101000100011001 5
b11111100011011011010110000000000100011101100010101000100010 6
1"
#556005
0"
#560005
b101100010011001010010010101001100000100000011100001111000110000 #
b101100010011001010010010101001100000100000011100001111000110000 (
b1000 4
b1011100001111111000010100100011 2
b10100101101111011011110101101000 3
b1011111000011001001000011110111 )
b10100101101111011011110101101000 0
b11001100110001010111010100 -
b1000 :
b10001100111011110010011110111011 9
b0 8
b1000 7
b11001100110001010111010100 5
b1100100111101101000000100100100011111100100101111001100110100111 6
1"
#564005
0"
#568005
b1001111110001111010111111111101110100101111110000000101000001010 #
b1001111110001111010111111111101110100101111110000000101000001010 (
b1000 4
b11010111111001111111001100001110 2
b1011111000011001001000011110111 3
b11001001100000010111111011000110 )
b1011111000011001001000011110111 0
b11110011001101000110111001000 -
b1000 :
b11101010001000011110000011100001 9
b0 8
b1000 7
b11110011001101000110111001000 5
b101100010011001010010010101001100000100000011100001111000110000 6
1"
#572005
0"
#576005
b1001110110100110000110001111110101111011111101111000101001001101 #
b1001110110100110000110001111110101111011111101111000101001001101 (
b1000 4
b110001011101111010100000010001 2
b11001001100000010111111011000110 3
b10101111111011011001001001111111 )
b11001001100000010111111011000110 0
b10011110100110100011101001101110 -
b1000 :
b11001001001101111111010101110 9
b0 8
b1000 7
b10011110100110100011101001101110 5
b1001111110001111010111111111101110100101111110000000101000001010 6
1"
#580005
0"
#584005
b10011000000111101011010101111101110110101010110001010001110101 #
b10011000000111101011010101111101110110101010110001010001110101 (
b1000 4
b1010101100010101110010000110010 2
b10101111111011011001001001111111 3
b1011101001110111011011011101001 )
b10101111111011011001001001111111 0
b1000101100010101001011011011 -
b1000 :
b10001111110000100001110110110111 9
b0 8
b1000 7
b1000101100010101001011011011 5
b1001110110100110000110001111110101111011111101111000101001001101 6
1"
#588005
0"
#592005
b10111011011111000001110100001100010111010111101001100101000001 #
b10111011011111000001110100001100010111010111101001100101000001 (
b1000 4
b1110001000001001011100011000100 2
b1011101001110111011011011101001 3
b11011100111011101010100101010010 )
b1011101001110111011011011101001 0
b10101101111010100001000110010110 -
b1000 :
b10110101001111010100110101000100 9
b0 8
b1000 7
b10101101111010100001000110010110 5
b10011000000111101011010101111101110110101010110001010001110101 6
1"
#596005
0"
#600005
b1110101001010001010110001001010110110101000100000101110110000 #
b1110101001010001010110001001010110110101000100000101110110000 (
b1000 4
b10100101011110111000101010101100 2
b11011100111011101010100101010010 3
b10001000110000000110110001101100 )
b11011100111011101010100101010010 0
b101101101110111110011011000000 -
b1000 :
b1110001001111111100011100100111 9
b0 8
b1000 7
b101101101110111110011011000000 5
b10111011011111000001110100001100010111010111101001100101000001 6
1"
#604005
0"
#608005
b1110111110000011100110011011011000011010001100001011001111 #
b1110111110000011100110011011011000011010001100001011001111 (
b1000 4
b1011011001011000111011010000010 2
b10001000110000000110110001101100 3
b11100011000101100100010011001101 )
b10001000110000000110110001101100 0
b10111000001110100011001001001111 -
b1000 :
b11110010110110001001111110111111 9
b0 8
b1000 7
b10111000001110100011001001001111 5
b1110101001010001010110001001010110110101000100000101110110000 6
1"
#612005
0"
#616005
b111110010011011101111111010111010000000110010100001011110110111 #
b111110010011011101111111010111010000000110010100001011110110111 (
b1000 4
b11101011000111000101111100000101 2
b11100011000101100100010011001101 3
b10111001101001100110101011001010 )
b11100011000101100100010011001101 0
b1010010101110100011010111001111 -
b1000 :
b10010011010010011101011000101 9
b0 8
b1000 7
b1010010101110100011010111001111 5
b1110111110000011100110011011011000011010001100001011001111 6
1"
#620005
0"
#624005
b1111011100000011110010011111111111100001011001101000001001110001 #
b1111011100000011110010011111111111100001011001101000001001110001 (
b1000 4
b10110001100101101000011000010 2
b10111001101001100110101011001010 3
b11000001010111011001100110100001 )
b10111001101001100110101011001010 0
b11010111011011110100100101100011 -
b1000 :
b1011110000111111000011111011111 9
b0 8
b1000 7
b11010111011011110100100101100011 5
b111110010011011101111111010111010000000110010100001011110110111 6
1"
#628005
0"
#632005
b1000010000111001001110101011000111111111101001011101110001100 #
b1000010000111001001110101011000111111111101001011101110001100 (
b1000 4
b1111000110100100000111010111111 2
b11000001010111011001100110100001 3
b10000100001101111111100100000000 )
b11000001010111011001100110100001 0
b11111100111001011111011110111111 -
b1000 :
b11010101110001110001110101001000 9
b0 8
b1000 7
b11111100111001011111011110111111 5
b1111011100000011110010011111111111100001011001101000001001110001 6
1"
#636005
0"
#640005
b1000101010000100110000010101110010101010110100010100001001101000 #
b1000101010000100110000010101110010101010110100010100001001101000 (
b1000 4
b10101100111111110101111001001101 2
b10000100001101111111100100000000 3
b10011101011110101011111100101001 )
b10000100001101111111100100000000 0
b110001100001011110000101100100 -
b1000 :
b1000011101001110000110100101011 9
b0 8
b1000 7
b110001100001011110000101100100 5
b1000010000111001001110101011000111111111101001011101110001100 6
1"
#644005
0"
#648005
b111011101000101001000001101011111101001100011010111110000110101 #
b111011101000101001000001101011111101001100011010111110000110101 (
b1000 4
b10110011001010111000101100110010 2
b10011101011110101011111100101001 3
b11000011011100000110011111001101 )
b10011101011110101011111100101001 0
b1110000010110111110110011111111 -
b1000 :
b1001101111100010001110011111000 9
b0 8
b1000 7
b1110000010110111110110011111111 5
b1000101010000100110000010101110010101010110100010100001001101000 6
1"
#652005
0"
#656005
b1001100111111001100000100011110000010001100011011100000100001110 #
b1001100111111001100000100011110000010001100011011100000100001110 (
b1000 4
b1010001001011011111101000111 2
b11000011011100000110011111001101 3
b10101011100010110110001010110110 )
b11000011011100000110011111001101 0
b10100001101011101101110111110001 -
b1000 :
b100101000100010110000010001110 9
b0 8
b1000 7
b10100001101011101101110111110001 5
b111011101000101001000001101011111101001100011010111110000110101 6
1"
#660005
0"
#664005
b1011011000100000010100011001110101100110101010001111001100110 #
b1011011000100000010100011001110101100110101010001111001100110 (
b1000 4
b1111111001100001100100001110000 2
b10101011100010110110001010110110 3
b11101011100111110000111010101010 )
b10101011100010110110001010110110 0
b10010100101011111100011011011010 -
b1000 :
b1011010110001011100101101001100 9
b0 8
b1000 7
b10010100101011111100011011011010 5
b1001100111111001100000100011110000010001100011011100000100001110 6
1"
#668005
0"
#672005
b1001010000111001100001010010000010000011110110011111110010100111 #
b1001010000111001100001010010000010000011110110011111110010100111 (
b1000 4
b11011000100001101101001001000001 2
b11101011100111110000111010101010 3
b10111010100011000001011001100111 )
b11101011100111110000111010101010 0
b1100010000010101100010000100110 -
b1000 :
b10001011111110011001101110101000 9
b0 8
b1000 7
b1100010000010101100010000100110 5
b1011011000100000010100011001110101100110101010001111001100110 6
1"
#676005
0"
#680005
b100010100000011100011100010001000001011110001000110001000011011 #
b100010100000011100011100010001000001011110001000110001000011011 (
b1000 4
b11101101001001011100010001000000 2
b10111010100011000001011001100111 3
b10010011001011100101000101101111 )
b10111010100011000001011001100111 0
b1111110000010111001010100101111 -
b1000 :
b10011101010001110110000010000000 9
b0 8
b1000 7
b1111110000010111001010100101111 5
b1001010000111001100001010010000010000011110110011111110010100111 6
1"
#684005
0"
#688005
b1000111001110010010111010101011111010011000010101010110101001011 #
b1000111001110010010111010101011111010011000010101010110101001011 (
b1000 4
b100111011010010110100110010010 2
b10010011001011100101000101101111 3
b101011001100111100001101110011 )
b10010011001011100101000101101111 0
b1100010110101010101011100001 -
b1000 :
b1101011001010000011100001110001 9
b0 8
b1000 7
b1100010110101010101011100001 5
b100010100000011100011100010001000001011110001000110001000011011 6
1"
#692005
0"
#696005
b1010010100000110101111111100010100010000001001011101101111100101 #
b1010010100000110101111111100010100010000001001011101101111100101 (
b1000 4
b11101011110101010111100001110011 2
b101011001100111100001101110011 3
b11110011001001110000110100100010 )
b101011001100111100001101110011 0
b11000111100100111010101010001 -
b1000 :
b11011011010011100100110011000101 9
b0 8
b1000 7
b11000111100100111010101010001 5
b1000111001110010010111010101011111010011000010101010110101001011 6
1"
#700005
0"
#704005
1%
b111101100100101001100110001111101001101011010111111110110001111 #
b111101100100101001100110001111101001101011010111111110110001111 (
b1000 4
b11001111101110010001101111101000 2
b11110011001001110000110100100010 3
b11100101101110110011001110101101 )
b11110011001001110000110100100010 0
b101010000000100010100001000101 -
b1000 :
b11100011100111000100110110 9
b0 8
b1000 7
b101010000000100010100001000101 5
b1010010100000110101111111100010100010000001001011101101111100101 6
1"
#708005
0"
#712005
0%
0&
b1000 4
b111000111110101110011010001011 2
b11100101101110110011001110101101 3
b1110100011010110010110111010110 )
b11100101101110110011001110101101 0
1.
b1001100100100011100101101011101 -
b1000 :
b100010001001000100111110100010 9
b0 8
b1000 7
b1001100100100011100101101011101 5
b111101100100101001100110001111101001101011010111111110110001111 6
1"
#716005
0"
#720005
b11010110010011001110101111001011 )
b1000 4
b10011010110111010010000010010110 2
b11111111111111111111111111111111 3
b11111111111111111111111111111111 0
b10001011100101001101001000101001 !
b10001011100101001101001000101001 /
0.
01
b1000 :
b1100010100100110010000010000001 9
b0 8
b1000 7
b1001100100100011100101101011101 5
1"
#724005
0"
#728005
b1000 :
b11111000110110110000001101011010 9
b1111011 8
b1000 7
b1001100100100011100101101011101 5
1"
#732005
0"
#736005
b1000 :
b11111000110110110000001101011010 9
b1111011 8
b1000 7
b1001100100100011100101101011101 5
1"
#740005
0"
#744005
1&
b1010011111001101101001101100001000111111110010000110111011100110 #
b1010011111001101101001101100001000111111110010000110111011100110 (
b1000 :
b11111000110110110000001101011010 9
b1111011 8
b1000 7
b1001100100100011100101101011101 5
1"
#748005
0"
#752005
b11001100110101010011111100011111101110111110101101111100100011 #
b11001100110101010011111100011111101110111110101101111100100011 (
b11101101011101100001000001010001 )
11
b1110111101010110011000011000111 -
b1000 :
b10101100000000000101000110100110 9
b10100111 8
b1000 7
b1110111101010110011000011000111 5
b1010011111001101101001101100001000111111110010000110111011100110 6
1"
#756005
0"
#760005
b1110000001100101111000111110101101110100000100010011110010110000 #
b1110000001100101111000111110101101110100000100010011110010110000 (
b1000 4
b11110011011011011000001000100100 2
b11101101011101100001000001010001 3
b1110111010011110110100000011110 )
b11101101011101100001000001010001 0
b10000100001000101110101000111010 -
b1000 :
b11010100111100110110110000010010 9
b0 8
b1000 7
b10000100001000101110101000111010 5
b11001100110101010011111100011111101110111110101101111100100011 6
1"
#764005
0"
#768005
b1010101001011000011010010101000110000111101110001010010100011000 #
b1010101001011000011010010101000110000111101110001010010100011000 (
b1000 4
b1100100100101001010010111111101 2
b1110111010011110110100000011110 3
b1011001000111111111000010111 )
b1110111010011110110100000011110 0
b1101111101101110101101111101010 -
b1000 :
b11111111000011010011110100011001 9
b0 8
b1000 7
b1101111101101110101101111101010 5
b1110000001100101111000111110101101110100000100010011110010110000 6
1"
#772005
0"
#776005
b1111000100000100100010101010011000000100111100001101000011110010 #
b1111000100000100100010101010011000000100111100001101000011110010 (
b1000 4
b10110100110101110011111100111111 2
b1011001000111111111000010111 3
b10001011100100110001000100110000 )
b1011001000111111111000010111 0
b111111010001000010111000001111 -
b1000 :
b11011100100000010000100011111100 9
b0 8
b1000 7
b111111010001000010111000001111 5
b1010101001011000011010010101000110000111101110001010010100011000 6
1"
#780005
0"
